tensorquant/__init__.py
tensorquant/analytics/__init__.py
tensorquant/analytics/gaussiankernel.py
tensorquant/analytics/rateexposure.py
tensorquant/flows/__init__.py
tensorquant/flows/cashflow.py
tensorquant/flows/coupon.py
tensorquant/flows/fixedcoupon.py
tensorquant/flows/floatingcoupon.py
tensorquant/index/__init__.py
tensorquant/index/curverateindex.py
tensorquant/index/index.py
tensorquant/index/inflationindex.py
tensorquant/instruments/__init__.py
tensorquant/instruments/capfloor.py
tensorquant/instruments/deposit.py
tensorquant/instruments/forward.py
tensorquant/instruments/helpers.py
tensorquant/instruments/ois.py
tensorquant/instruments/option.py
tensorquant/instruments/product.py
tensorquant/instruments/swap.py
tensorquant/markethandles/__init__.py
tensorquant/markethandles/bootstrapping.py
tensorquant/markethandles/interestrate.py
tensorquant/markethandles/ircurve.py
tensorquant/markethandles/utils.py
tensorquant/markethandles/volatilitysurface.py
tensorquant/models/__init__.py
tensorquant/models/brownian.py
tensorquant/models/hullwhite.py
tensorquant/models/ornsteinuhlenbeck.py
tensorquant/models/stochasticprocess.py
tensorquant/numericalhandles/__init__.py
tensorquant/numericalhandles/interpolation.py
tensorquant/numericalhandles/newton.py
tensorquant/pricers/__init__.py
tensorquant/pricers/black.py
tensorquant/pricers/deposit.py
tensorquant/pricers/factory.py
tensorquant/pricers/fixedflow.py
tensorquant/pricers/floatingflow.py
tensorquant/pricers/fradiscounting.py
tensorquant/pricers/pricer.py
tensorquant/pricers/swapdiscounting.py
tensorquant/timehandles/__init__.py
tensorquant/timehandles/daycounter.py
tensorquant/timehandles/grid.py
tensorquant/timehandles/schedule.py
tensorquant/timehandles/targetcalendar.py
tensorquant/timehandles/tqcalendar.py
tensorquant/timehandles/utils.py
tests/__init__.py
tests/test_deposit.py
tensorquant-0.0.6.dist-info/LICENSE
tensorquant-0.0.6.dist-info/METADATA
tensorquant-0.0.6.dist-info/WHEEL
tensorquant-0.0.6.dist-info/top_level.txt
tensorquant-0.0.6.dist-info/RECORD
