Metadata-Version: 2.1
Name: tensorquant
Version: 0.0.6
Summary: TensorFlow-Python financial library
Home-page: https://github.com/andrea220/tQuant
Author: Andrea Carapelli
Author-email: carapelliandrea@email.com
Classifier: Programming Language :: Python :: 3
Classifier: License :: OSI Approved :: GNU General Public License v3 (GPLv3)
Classifier: Operating System :: OS Independent
Requires-Python: >=3.10
License-File: LICENSE
Requires-Dist: tensorflow (>=2.0)
Requires-Dist: tensorflow-probability (>=0.20)
Requires-Dist: pandas
Requires-Dist: python-dateutil
